stcutils/__init__.py
stcutils-20220928.dist-info/LICENSE.txt
stcutils-20220928.dist-info/METADATA
stcutils-20220928.dist-info/WHEEL
stcutils-20220928.dist-info/top_level.txt
stcutils-20220928.dist-info/RECORD
