Metadata-Version: 2.1
Name: stcutils
Version: 20220928
Summary: Provide useful functionality and auto testing data for my computer science students. Designed for Sha Tin College.
Home-page: https://github.com/paulbaumgarten/stc-tester
Author: Paul Baumgarten
Author-email: pbaumgarten@gmail.com
License: UNKNOWN
Keywords: Sha Tin College
Platform: UNKNOWN
Classifier: Programming Language :: Python :: 3
Classifier: License :: OSI Approved :: MIT License
Classifier: Operating System :: OS Independent
Requires-Python: >=3
Requires-Dist: requests
